fridaay/__init__.py
fridaay/constants.py
fridaay/dad/dad-core.yml
fridaay/dad/dad-sql.yml
fridaay/load.py
fridaay/pipe.py
fridaay/pipes/demo_pets.yml
fridaay/registry.py
fridaay/schema.py
fridaay-0.2.3.dist-info/LICENSE
fridaay-0.2.3.dist-info/WHEEL
fridaay-0.2.3.dist-info/METADATA
fridaay-0.2.3.dist-info/RECORD
