Metadata-Version: 2.1
Name: fridaay
Version: 0.2.3
Summary: Format Representing Interdependent Data Actions As YAML
Home-page: https://github.com/TheSwanFactory/fridaay
License: MIT
Author: Ernest Prabhakar
Author-email: ernest.prabhakar@gmail.com
Requires-Python: >=3.9,<4.0
Classifier: License :: OSI Approved :: MIT License
Classifier: Programming Language :: Python :: 3
Classifier: Programming Language :: Python :: 3.10
Classifier: Programming Language :: Python :: 3.9
Requires-Dist: PyYAML (>=6.0,<7.0)
Requires-Dist: click (>=8.1.3,<9.0.0)
Requires-Dist: dad-sql-pandas (>=0.1.1,<0.2.0)
Project-URL: Repository, https://github.com/TheSwanFactory/fridaay
